py4jasper/__init__.py
py4jasper/main.py
tests/__init__.py
tests/test_generate_report.py
py4jasper-1.0.0.0.dist-info/METADATA
py4jasper-1.0.0.0.dist-info/WHEEL
py4jasper-1.0.0.0.dist-info/top_level.txt
py4jasper-1.0.0.0.dist-info/RECORD
