Metadata-Version: 2.1
Name: py4jasper
Version: 1.0.0.0
Summary: Python package for generating reports using Jasper
Author: Sanskar Gandhi
Author-email: sanskargandhi2000@gmail.com
Classifier: Programming Language :: Python :: 3
Classifier: License :: OSI Approved :: MIT License
Classifier: Operating System :: OS Independent
Requires-Python: >=3.7
Requires-Dist: py4j
